eclypse_html_report/__init__.py
eclypse_html_report/cli.py
eclypse_html_report/node_group.py
eclypse_html_report/report.py
eclypse_html_report/tools.py
eclypse_html_report/types.py
eclypse_html_report-0.1.3.dist-info/LICENSE
eclypse_html_report-0.1.3.dist-info/METADATA
eclypse_html_report-0.1.3.dist-info/WHEEL
eclypse_html_report-0.1.3.dist-info/entry_points.txt
eclypse_html_report-0.1.3.dist-info/RECORD
