Metadata-Version: 2.1
Name: eclypse-html-report
Version: 0.1.3
Summary: A tool to generate an HTML report from the results of an ECLYPSE simulation
Home-page: https://github.com/eclypse-org/eclypse-html-report
License: MIT
Author: Valerio De Caro
Author-email: valerio.decaro@di.unipi.it
Maintainer: Valerio De Caro
Maintainer-email: valerio.decaro@di.unipi.it
Requires-Python: >=3.9,<3.12
Classifier: License :: OSI Approved :: MIT License
Classifier: Programming Language :: Python :: 3
Classifier: Programming Language :: Python :: 3.9
Classifier: Programming Language :: Python :: 3.10
Classifier: Programming Language :: Python :: 3.11
Requires-Dist: click (>=8.1.7,<9.0.0)
Requires-Dist: datapane (>=0.17.0,<0.18.0)
Requires-Dist: numpy (<=1.26.4)
Requires-Dist: plotly (>=5.24.1,<6.0.0)
Requires-Dist: pyvis (>=0.3.2,<0.4.0)
Project-URL: Repository, https://github.com/eclypse-org/eclypse-html-report
